MultiCalib/Camera.py
MultiCalib/CameraSystemCalibration.py
MultiCalib/Pattern.py
MultiCalib/__init__.py
MultiCalib/utils.py
MultiCalib-0.1.1.dist-info/METADATA
MultiCalib-0.1.1.dist-info/WHEEL
MultiCalib-0.1.1.dist-info/top_level.txt
MultiCalib-0.1.1.dist-info/RECORD
