Metadata-Version: 2.1
Name: MultiCalib
Version: 0.1.1
Summary: A Python library for multi-camera system calibration with high accuracy.
Home-page: https://github.com/stanleydukor/MultiCalib
Author: Obumneme Dukor
Author-email: stanleydukor@gmail.com
Classifier: Programming Language :: Python :: 3
Classifier: License :: OSI Approved :: MIT License
Classifier: Operating System :: OS Independent
Requires-Python: >=3.6
Requires-Dist: matplotlib ==3.7.5
Requires-Dist: networkx ==3.1
Requires-Dist: numpy ==1.23.5
Requires-Dist: opencv-python ==4.7.0.72
Requires-Dist: scikit-learn ==1.3.0
Requires-Dist: scipy ==1.10.1
Requires-Dist: PyYAML ==6.0
